YongJerseyGoujianRestfulFuwu/README.md
YongJerseyGoujianRestfulFuwu/__init__.py
YongJerseyGoujianRestfulFuwu/__main__.py
YongJerseyGoujianRestfulFuwu/file.epub
YongJerseyGoujianRestfulFuwu/index.html
YongJerseyGoujianRestfulFuwu/css/__init__.py
YongJerseyGoujianRestfulFuwu/css/annotations.css
YongJerseyGoujianRestfulFuwu/css/main.css
YongJerseyGoujianRestfulFuwu/css/normalize.css
YongJerseyGoujianRestfulFuwu/css/popup.css
YongJerseyGoujianRestfulFuwu/font/__init__.py
YongJerseyGoujianRestfulFuwu/font/fontello.eot
YongJerseyGoujianRestfulFuwu/font/fontello.svg
YongJerseyGoujianRestfulFuwu/font/fontello.ttf
YongJerseyGoujianRestfulFuwu/font/fontello.woff
YongJerseyGoujianRestfulFuwu/img/__init__.py
YongJerseyGoujianRestfulFuwu/img/annotator-glyph-sprite.png
YongJerseyGoujianRestfulFuwu/img/annotator-icon-sprite.png
YongJerseyGoujianRestfulFuwu/img/apple-touch-icon.png
YongJerseyGoujianRestfulFuwu/img/cancelfullscreen.png
YongJerseyGoujianRestfulFuwu/img/close.png
YongJerseyGoujianRestfulFuwu/img/fullscreen.png
YongJerseyGoujianRestfulFuwu/img/loader.gif
YongJerseyGoujianRestfulFuwu/img/menu-icon.png
YongJerseyGoujianRestfulFuwu/img/save.png
YongJerseyGoujianRestfulFuwu/img/saved.png
YongJerseyGoujianRestfulFuwu/img/settings-s.png
YongJerseyGoujianRestfulFuwu/img/settings.png
YongJerseyGoujianRestfulFuwu/img/star.png
YongJerseyGoujianRestfulFuwu/js/__init__.py
YongJerseyGoujianRestfulFuwu/js/epub.js
YongJerseyGoujianRestfulFuwu/js/epub.min.js
YongJerseyGoujianRestfulFuwu/js/epub.min.map
YongJerseyGoujianRestfulFuwu/js/hooks.min.js
YongJerseyGoujianRestfulFuwu/js/hooks.min.map
YongJerseyGoujianRestfulFuwu/js/reader.js
YongJerseyGoujianRestfulFuwu/js/reader.js.map
YongJerseyGoujianRestfulFuwu/js/reader.min.js
YongJerseyGoujianRestfulFuwu/js/reader.min.map
YongJerseyGoujianRestfulFuwu/js/hooks/__init__.py
YongJerseyGoujianRestfulFuwu/js/hooks/extensions/__init__.py
YongJerseyGoujianRestfulFuwu/js/hooks/extensions/highlight.js
yong_jersey_goujian_restful_fuwu-2024.3.2.0.dist-info/METADATA
yong_jersey_goujian_restful_fuwu-2024.3.2.0.dist-info/WHEEL
yong_jersey_goujian_restful_fuwu-2024.3.2.0.dist-info/entry_points.txt
yong_jersey_goujian_restful_fuwu-2024.3.2.0.dist-info/top_level.txt
yong_jersey_goujian_restful_fuwu-2024.3.2.0.dist-info/RECORD
